aide_validation/__init__.py
aide_validation/floc_validation.py
aide_validation/lfom_validation.py
aide_validation/link_input.py
aide_validation/report_writer.py
aide_validation/sed_validation.py
aide_validation/validator.py
aide_validation-0.0.1.dist-info/LICENSE
aide_validation-0.0.1.dist-info/METADATA
aide_validation-0.0.1.dist-info/WHEEL
aide_validation-0.0.1.dist-info/top_level.txt
aide_validation-0.0.1.dist-info/RECORD
